<?xml version="1.0" encoding="UTF-8"?>
<!DOCTYPE language SYSTEM "language.dtd">
<!-- Extended and updated by                                    -->
<!-- Christoph Hormann <chris_hormann@gmx.de>, March 2004       -->
<!-- features full POV-Ray 3.6 syntax with special highlighting -->
<!-- of variable and macro declarations                         -->
<!-- v1.1: added MegaPOV 1.2.1 keywords (Febuary 2006)          -->
	<language name="minizinc" version="5" kateversion="2.4" section="3D" extensions="*.inc;*.pov" mimetype="text/x-minizinc" author="Joan Arnaldich" license="LGPL" priority="2">
	<highlighting>

		<list name="keywords">
			<item>predicate</item>
			<item>constraint</item>
			<item>of</item>
			<item>in</item>
		</list>

		<list name="types">
			<item>array</item>
			<item>int</item>
			<item>float</item>
			<item>set</item>
			<item>enum</item>
		</list>

		<list name="typemods">
			<item>var</item>
		</list>

		<list name="builtins">
			<item>min</item>
			<item>max</item>
			<item>array2d</item>
		</list>

		<list name="control">
			<item>exists</item>
			<item>foreach</item>
		</list>

		<contexts>
			<context attribute="Normal Text" lineEndContext="#stay" name="Normal">
				<keyword attribute="Keywords" context="#stay" String="keywords" />
				<keyword attribute="Types" context="#stay" String="types" />
				<keyword attribute="TypeMods" context="#stay" String="typemods" />
				<keyword attribute="BuiltIns" context="#stay" String="builtins" />
				<keyword attribute="Control" context="#stay" String="control" />
				<Float attribute="Float" context="#stay"/>
				<Int attribute="Float" context="#stay"/>
			</context>
		</contexts>

		<itemDatas>
			<itemData name="Normal Text"     defStyleNum="dsNormal"   color="#000000" selColor="#ffffff" bold="0" italic="0"/>
			<itemData name="Keywords"         defStyleNum="dsKeyword"  color="#000080" selColor="#ffffff" bold="0" italic="0"/>
			<itemData name="Types"      defStyleNum="dsKeyword"  color="#0080d0" selColor="#ffffff" bold="0" italic="0"/>
			<itemData name="TypeMods"      defStyleNum="dsKeyword"  color="#000080" selColor="#ffffff" bold="0" italic="0"/>
			<itemData name="BuiltIns"         defStyleNum="dsKeyword"  color="#800000" selColor="#ffffff" bold="0" italic="0"/>
			<itemData name="Control"       defStyleNum="dsControlFlow"  color="#000080" selColor="#ffffff" bold="0" italic="0"/>
			<itemData name="Float"           defStyleNum="dsFloat"    color="#0000ff" selColor="#ffffff" bold="0" italic="0"/>
		</itemDatas>
	</highlighting>

	<general>
		<comments>
			<comment name="singleLine" start="%" />
			<comment name="multiLine" start="/*" end="*/" />
		</comments>

		<keywords casesensitive="1" />
	</general>
</language>
